[
	{
		"name": "The Wheels of the Prescripts",
		"replaces": "Grand Temple",
		"uniqueTo": "The Index",
		"cost": 90,
		"happiness": 4,
		"culture": 1,
		"faith": 8,
		"isNationalWonder": true,
		"requiredBuildingInAllCities": "Temple",
		"requiredTech": "Theology",
		"uniques": ["Only available <if [Temple] is constructed in all [non-[Puppeted]] cities>", 
			    "Cost increases by [30] per owned city",
			    "[+100]% Natural religion spread [in this city]", 
			    "Only available <when religion is enabled>", "Can only be built <in [Holy] cities>"],
	}
]
